[
  {
    "title": "海亮股份(002203.SZ)：第二期员工持股计划锁定期于11月16日届满",
    "href": "http://stock.jrj.com.cn/2022/11/15162037140419.shtml",
    "datetime": "2022-11-15 16:20:50",
    "code": "002203"
  },
  {
    "title": "海亮股份(002203.SZ)：拟将不超6亿元闲置募资补充流动资金",
    "href": "http://stock.jrj.com.cn/2022/09/06185636977815.shtml",
    "datetime": "2022-09-06 18:56:49",
    "code": "002203"
  },
  {
    "title": "海亮股份(002203.SZ)：上半年净利润增4.72%至6.51亿元",
    "href": "http://stock.jrj.com.cn/2022/08/30010736949978.shtml",
    "datetime": "2022-08-30 01:07:37",
    "code": "002203"
  },
  {
    "title": "海亮股份(002203.SZ)：2021年年度权益分派10派0.75元 股权登记日6月29日",
    "href": "http://stock.jrj.com.cn/2022/06/22192236750684.shtml",
    "datetime": "2022-06-22 19:22:17",
    "code": "002203"
  },
  {
    "title": "海亮股份(002203.SZ)：子公司甘肃海亮取得19亿元银团贷款",
    "href": "http://stock.jrj.com.cn/2022/05/18181536659496.shtml",
    "datetime": "2022-05-18 18:15:04",
    "code": "002203"
  },
  {
    "title": "海亮股份(002203.SZ)：一季度净利升15.07%至3.12亿元",
    "href": "http://stock.jrj.com.cn/2022/04/29181436505858.shtml",
    "datetime": "2022-04-29 18:14:44",
    "code": "002203"
  },
  {
    "title": "海亮股份2021年净利11.07亿同比增长63.36% 董事长朱张泉薪酬150.96万",
    "href": "http://stock.jrj.com.cn/2022/04/28165236493497.shtml",
    "datetime": "2022-04-28 16:52:51",
    "code": "002203"
  },
  {
    "title": "海亮股份(002203.SZ)2021年度净利升63.36%至11.07亿元 拟10派0.75元",
    "href": "http://stock.jrj.com.cn/2022/04/28075536489859.shtml",
    "datetime": "2022-04-28 07:55:49",
    "code": "002203"
  },
  {
    "title": "海亮股份(002203.SZ)：控股股东因可交债换股被动减持达5%",
    "href": "http://stock.jrj.com.cn/2022/04/18121236380330.shtml",
    "datetime": "2022-04-18 12:12:37",
    "code": "002203"
  },
  {
    "title": "海亮股份(002203.SZ)：控股股东质押7475万股",
    "href": "http://stock.jrj.com.cn/2022/03/25214635158851.shtml",
    "datetime": "2022-03-25 21:46:04",
    "code": "002203"
  },
  {
    "title": "海亮股份控股股东海亮集团质押7475万股 用于融资担保",
    "href": "http://stock.jrj.com.cn/2022/03/25211235152993.shtml",
    "datetime": "2022-03-25 21:12:50",
    "code": "002203"
  },
  {
    "title": "海亮股份(002203.SZ)：全资子公司通过高新技术企业认定",
    "href": "http://stock.jrj.com.cn/2022/01/25161634210129.shtml",
    "datetime": "2022-01-25 16:16:50",
    "code": "002203"
  },
  {
    "title": "海亮股份2021年预计净利10.84亿-12.2亿同比增长60%-80% 产品销量增长",
    "href": "http://stock.jrj.com.cn/2022/01/21203034184123.shtml",
    "datetime": "2022-01-21 20:30:04",
    "code": "002203"
  },
  {
    "title": "海亮股份(002203.SZ)：2021年度净利预增60%-80%",
    "href": "http://stock.jrj.com.cn/2022/01/21172934183217.shtml",
    "datetime": "2022-01-21 17:29:00",
    "code": "002203"
  },
  {
    "title": "海亮股份(002203.SZ)：杭州涵智以3.22亿元投资蜂巢能源",
    "href": "http://stock.jrj.com.cn/2022/01/17203634166096.shtml",
    "datetime": "2022-01-17 20:36:39",
    "code": "002203"
  },
  {
    "title": "海亮股份(002203.SZ)：股东基金会于12月24日减持2%股份 持股降至5%以下",
    "href": "http://stock.jrj.com.cn/2021/12/27183134071783.shtml",
    "datetime": "2021-12-27 18:31:59",
    "code": "002203"
  },
  {
    "title": "海亮股份(002203.SZ)：控股股东及其一致行动人的持股比例从39.25%减少至38.2%",
    "href": "http://stock.jrj.com.cn/2021/12/15174434020100.shtml",
    "datetime": "2021-12-15 17:44:50",
    "code": "002203"
  },
  {
    "title": "海亮股份(002203.SZ)：拟出资1亿元参投新能源产业基金",
    "href": "http://stock.jrj.com.cn/2021/12/09212133991599.shtml",
    "datetime": "2021-12-09 21:21:17",
    "code": "002203"
  },
  {
    "title": "海亮股份(002203.SZ)：回购账户的3666.1544万股已过户至第二期员工持股计划专户",
    "href": "http://stock.jrj.com.cn/2021/11/18164133872828.shtml",
    "datetime": "2021-11-18 16:41:59",
    "code": "002203"
  },
  {
    "title": "海亮股份89亿投建锂电铜箔抢抓机遇 借供应链优势克服铜涨价净利增70%",
    "href": "http://stock.jrj.com.cn/2021/11/11073633834709.shtml",
    "datetime": "2021-11-11 07:36:27",
    "code": "002203"
  },
  {
    "title": "“宁王”豪掷150亿扩产；片仔癀控股股东减持；3连板易尚展示提示风险；海亮股份拟投建高性能铜箔材料项目",
    "href": "http://stock.jrj.com.cn/2021/11/08081033821755.shtml",
    "datetime": "2021-11-08 08:10:00",
    "code": "002203"
  },
  {
    "title": "海亮股份(002203.SZ)：拟投资89亿元建年产15万吨高性能铜箔材料项目",
    "href": "http://stock.jrj.com.cn/2021/11/07165933820241.shtml",
    "datetime": "2021-11-07 16:59:49",
    "code": "002203"
  },
  {
    "title": "海亮股份：拟投资建设年产15万吨高性能铜箔材料项目",
    "href": "http://stock.jrj.com.cn/2021/11/07164433820201.shtml",
    "datetime": "2021-11-07 16:44:56",
    "code": "002203"
  },
  {
    "title": "海亮股份：本次限制性股票上市流通日为11月9日 占公司总股本3.14%",
    "href": "http://stock.jrj.com.cn/2021/11/04175233813723.shtml",
    "datetime": "2021-11-04 17:52:21",
    "code": "002203"
  },
  {
    "title": "海亮股份(002203.SZ)：6180.47万股限售股11月9日解禁",
    "href": "http://stock.jrj.com.cn/2021/11/04172233813258.shtml",
    "datetime": "2021-11-04 17:22:08",
    "code": "002203"
  },
  {
    "title": "海亮股份(002203.SZ)：前三季度净利升70.09%至9.23亿元",
    "href": "http://stock.jrj.com.cn/2021/10/29171633778112.shtml",
    "datetime": "2021-10-29 17:16:37",
    "code": "002203"
  },
  {
    "title": "海亮股份(002203.SZ)：前三季度净利预增60%-80%",
    "href": "http://stock.jrj.com.cn/2021/10/13182533685924.shtml",
    "datetime": "2021-10-13 18:25:35",
    "code": "002203"
  },
  {
    "title": "海亮股份(002203.SZ)：控股股东及其一致行动人的持股比例从40.33%减少至39.25%",
    "href": "http://stock.jrj.com.cn/2021/09/09192233410841.shtml",
    "datetime": "2021-09-09 19:22:23",
    "code": "002203"
  },
  {
    "title": "海亮股份(002203.SZ)：拟使用不超9.8亿元闲置募集资金暂补流动资金",
    "href": "http://stock.jrj.com.cn/2021/09/07154833398530.shtml",
    "datetime": "2021-09-07 15:48:41",
    "code": "002203"
  },
  {
    "title": "海亮股份2021年半年度净利6.22亿元 同比净利增加71.10%",
    "href": "http://stock.jrj.com.cn/2021/08/30215933355570.shtml",
    "datetime": "2021-08-30 21:59:42",
    "code": "002203"
  },
  {
    "title": "海亮股份(002203.SZ)上半年净利升71.10%至6.22亿元",
    "href": "http://stock.jrj.com.cn/2021/08/30215033355521.shtml",
    "datetime": "2021-08-30 21:50:50",
    "code": "002203"
  },
  {
    "title": "海亮股份(002203.SZ)：第五代连铸连轧精密铜管生产线获中国有色金属工业协会“国际领先水平”评价",
    "href": "http://stock.jrj.com.cn/2021/07/29192733170776.shtml",
    "datetime": "2021-07-29 19:27:53",
    "code": "002203"
  },
  {
    "title": "海亮股份：上半年净利润预计同比增长60%-80%",
    "href": "http://stock.jrj.com.cn/2021/07/14101033093610.shtml",
    "datetime": "2021-07-14 10:10:00",
    "code": "002203"
  },
  {
    "title": "海亮股份2021年上半年预计净利增长60%-80% 下游需求复苏态势总体良好",
    "href": "http://stock.jrj.com.cn/2021/07/13203733090886.shtml",
    "datetime": "2021-07-13 20:37:54",
    "code": "002203"
  },
  {
    "title": "海亮股份(002203.SZ)半年度净利润预增60%-80%",
    "href": "http://stock.jrj.com.cn/2021/07/13174833090001.shtml",
    "datetime": "2021-07-13 17:48:13",
    "code": "002203"
  },
  {
    "title": "海亮股份(002203.SZ)2020年度权益分派10派0.75元 股权登记日为6月22日",
    "href": "http://stock.jrj.com.cn/2021/06/15192732936187.shtml",
    "datetime": "2021-06-15 19:27:25",
    "code": "002203"
  },
  {
    "title": "海亮股份：新合资公司能有效借助海亮公司的管理优势实现生产效能的显著提升",
    "href": "http://stock.jrj.com.cn/2021/05/14103932753806.shtml",
    "datetime": "2021-05-14 10:39:01",
    "code": "002203"
  },
  {
    "title": "海亮股份：目前合资公司产品主要为大盘重小口径的内螺纹铜管和光管",
    "href": "http://stock.jrj.com.cn/2021/05/14102932753532.shtml",
    "datetime": "2021-05-14 10:29:41",
    "code": "002203"
  },
  {
    "title": "海亮股份：合资公司将对奥博特原有的铜管生产基地进行全面改造升级",
    "href": "http://stock.jrj.com.cn/2021/05/14102832753531.shtml",
    "datetime": "2021-05-14 10:28:53",
    "code": "002203"
  },
  {
    "title": "海亮股份(002203.SZ)拟出资7亿元与奥博特设立合资公司",
    "href": "http://stock.jrj.com.cn/2021/05/09170832719242.shtml",
    "datetime": "2021-05-09 17:08:58",
    "code": "002203"
  },
  {
    "title": "海亮股份：与奥博特设立合资公司",
    "href": "http://stock.jrj.com.cn/2021/05/09165232719192.shtml",
    "datetime": "2021-05-09 16:52:20",
    "code": "002203"
  },
  {
    "title": "海亮股份(002203.SZ)：一季度净利2.71亿元 同比增长61.09%",
    "href": "http://stock.jrj.com.cn/2021/04/29214832482743.shtml",
    "datetime": "2021-04-29 21:48:16",
    "code": "002203"
  },
  {
    "title": "海亮股份2021年第一季度预计净利增长50%-70% 产品产销量增长",
    "href": "http://stock.jrj.com.cn/2021/04/16231332389376.shtml",
    "datetime": "2021-04-16 23:13:51",
    "code": "002203"
  },
  {
    "title": "海亮股份聘任孙洪钧为副总经理",
    "href": "http://stock.jrj.com.cn/2021/04/16211732388841.shtml",
    "datetime": "2021-04-16 21:17:00",
    "code": "002203"
  },
  {
    "title": "海亮股份2020年度净利减少36.48% 海运运费大幅攀升",
    "href": "http://stock.jrj.com.cn/2021/04/15195732381318.shtml",
    "datetime": "2021-04-15 19:57:08",
    "code": "002203"
  },
  {
    "title": "海亮股份：2017-2019年,公司三年累计分红6.76亿元",
    "href": "http://stock.jrj.com.cn/2021/03/22151232194225.shtml",
    "datetime": "2021-03-22 15:12:25",
    "code": "002203"
  },
  {
    "title": "海亮股份：公司目前合理匹配现有订单及生产需要的原料库存",
    "href": "http://stock.jrj.com.cn/2021/03/22151232194224.shtml",
    "datetime": "2021-03-22 15:12:06",
    "code": "002203"
  },
  {
    "title": "海亮股份：公司现阶段在手订单饱满",
    "href": "http://stock.jrj.com.cn/2021/03/22151132194223.shtml",
    "datetime": "2021-03-22 15:11:45",
    "code": "002203"
  },
  {
    "title": "海亮股份：公司采用“以销定产”的经营模式、“原材料价格+加工费”的销售定价模式",
    "href": "http://stock.jrj.com.cn/2021/02/19171031993319.shtml",
    "datetime": "2021-02-19 17:10:50",
    "code": "002203"
  },
  {
    "title": "海亮股份控股股东海亮集团质押2600万股 用于可交换公司债券事项补充担保",
    "href": "http://stock.jrj.com.cn/2021/01/14213031693841.shtml",
    "datetime": "2021-01-14 21:30:22",
    "code": "002203"
  },
  {
    "title": "海亮股份(002203.SZ)：控股股东质押2600万股用于可交债补充担保",
    "href": "http://stock.jrj.com.cn/2021/01/14172631692510.shtml",
    "datetime": "2021-01-14 17:26:23",
    "code": "002203"
  },
  {
    "title": "[海亮股份]深情关爱 殷殷期待 | 色尼区领导看望天马援藏班学生",
    "href": "http://stock.jrj.com.cn/2020/12/11000031466124.shtml",
    "datetime": "2020-12-11 00:00:00",
    "code": "002203"
  },
  {
    "title": "[海亮股份]曹建国、朱张泉分别当选为中国有色金属加工工业协会名誉理事长、副理事长",
    "href": "http://stock.jrj.com.cn/2020/11/19000031324103.shtml",
    "datetime": "2020-11-19 00:00:00",
    "code": "002203"
  },
  {
    "title": "海亮股份(002203.SZ)：967.42万股限制性股票将解除限售上市流通",
    "href": "http://stock.jrj.com.cn/2020/11/08170231237180.shtml",
    "datetime": "2020-11-08 17:02:50",
    "code": "002203"
  },
  {
    "title": "海亮股份(002203.SZ)：967.42万股限制性股票解除限售条件成就",
    "href": "http://stock.jrj.com.cn/2020/11/02191631202215.shtml",
    "datetime": "2020-11-02 19:16:01",
    "code": "002203"
  },
  {
    "title": "海亮股份2020年前三季度净利5.42亿下滑33.93% 投资收益同比下滑",
    "href": "http://stock.jrj.com.cn/2020/11/01165931184214.shtml",
    "datetime": "2020-11-01 16:59:01",
    "code": "002203"
  },
  {
    "title": "[海亮股份]两天开出8家社区生鲜店!明康汇加速扩张步伐",
    "href": "http://stock.jrj.com.cn/2020/10/30000031210191.shtml",
    "datetime": "2020-10-30 00:00:00",
    "code": "002203"
  },
  {
    "title": "[海亮股份]冯亚丽当选浙江省侨界“十杰”",
    "href": "http://stock.jrj.com.cn/2020/10/21000031100724.shtml",
    "datetime": "2020-10-21 00:00:00",
    "code": "002203"
  },
  {
    "title": "[海亮股份]中国财务公司协会监事会莅临海亮财务公司调研",
    "href": "http://stock.jrj.com.cn/2020/10/16000031067924.shtml",
    "datetime": "2020-10-16 00:00:00",
    "code": "002203"
  },
  {
    "title": "[海亮股份]社会心理服务体系建设督察组莅临海亮融爱调研",
    "href": "http://stock.jrj.com.cn/2020/10/14000031061931.shtml",
    "datetime": "2020-10-14 00:00:00",
    "code": "002203"
  },
  {
    "title": "[海亮股份]中秋逢国庆,海亮家人这样庆祝“中国节”",
    "href": "http://stock.jrj.com.cn/2020/10/02000031029130.shtml",
    "datetime": "2020-10-02 00:00:00",
    "code": "002203"
  },
  {
    "title": "[海亮股份]喜迎“双节”︱海亮集团举行员工小球类比赛和徒步活动",
    "href": "http://stock.jrj.com.cn/2020/09/30000030868708.shtml",
    "datetime": "2020-09-30 00:00:00",
    "code": "002203"
  },
  {
    "title": "[海亮股份]安徽省蚌埠市市长王诚到海亮集团调研",
    "href": "http://stock.jrj.com.cn/2020/09/26000030853637.shtml",
    "datetime": "2020-09-26 00:00:00",
    "code": "002203"
  },
  {
    "title": "[海亮股份]海亮的大爱 “星儿”的希望 | “星援助计划”首期公益班开班",
    "href": "http://stock.jrj.com.cn/2020/09/25000030853638.shtml",
    "datetime": "2020-09-25 00:00:00",
    "code": "002203"
  },
  {
    "title": "[海亮股份]海亮集团与苹果公司深入交流、探索合作可能",
    "href": "http://stock.jrj.com.cn/2020/09/24000030852595.shtml",
    "datetime": "2020-09-24 00:00:00",
    "code": "002203"
  },
  {
    "title": "[海亮股份]对舞弊行为零容忍 | “海亮集团除名查询系统”正式上线",
    "href": "http://stock.jrj.com.cn/2020/09/04000030677316.shtml",
    "datetime": "2020-09-04 00:00:00",
    "code": "002203"
  },
  {
    "title": "[海亮股份]全国人大常委会执法检查组莅临海亮幸福院调研",
    "href": "http://stock.jrj.com.cn/2020/08/28000030653527.shtml",
    "datetime": "2020-08-28 00:00:00",
    "code": "002203"
  },
  {
    "title": "海亮股份2020年上半年净利3.64亿下滑43.53% 管理费用增长",
    "href": "http://stock.jrj.com.cn/2020/08/27143930604132.shtml",
    "datetime": "2020-08-27 14:39:56",
    "code": "002203"
  },
  {
    "title": "[海亮股份]浙江省侨联党组书记、主席连小敏莅临海亮集团考察",
    "href": "http://stock.jrj.com.cn/2020/08/25000030589479.shtml",
    "datetime": "2020-08-25 00:00:00",
    "code": "002203"
  },
  {
    "title": "[海亮股份]优势互补 资源共享 | 海亮集团与浙江联通签署战略合作协议",
    "href": "http://stock.jrj.com.cn/2020/08/12000030556560.shtml",
    "datetime": "2020-08-12 00:00:00",
    "code": "002203"
  },
  {
    "title": "[海亮股份]海亮集团上榜世界500强,排名提升5位",
    "href": "http://stock.jrj.com.cn/2020/08/11000030472562.shtml",
    "datetime": "2020-08-11 00:00:00",
    "code": "002203"
  },
  {
    "title": "[海亮股份]喜讯!《财富》中国500强揭晓:海亮股份位列第241位",
    "href": "http://stock.jrj.com.cn/2020/07/28000030367258.shtml",
    "datetime": "2020-07-28 00:00:00",
    "code": "002203"
  },
  {
    "title": "[海亮股份]激浊扬清 从善如流 | 海亮集团召开廉正大会",
    "href": "http://stock.jrj.com.cn/2020/07/25000030355577.shtml",
    "datetime": "2020-07-25 00:00:00",
    "code": "002203"
  },
  {
    "title": "[海亮股份]科技高地 携手并进 | 海亮集团与诸暨市高新区管委会签署合作协议",
    "href": "http://stock.jrj.com.cn/2020/07/25000030345193.shtml",
    "datetime": "2020-07-25 00:00:00",
    "code": "002203"
  },
  {
    "title": "[海亮股份]省委统战部副部长、省工商联党组书记陈浩调研海亮集团",
    "href": "http://stock.jrj.com.cn/2020/07/11000030224113.shtml",
    "datetime": "2020-07-11 00:00:00",
    "code": "002203"
  },
  {
    "title": "[国茂股份]海亮股份与国茂股份 首台(套)高速行星轧管机交付仪式在国茂股份圆满举行",
    "href": "http://stock.jrj.com.cn/2020/07/06000031083649.shtml",
    "datetime": "2020-07-06 00:00:00",
    "code": "002203"
  },
  {
    "title": "海亮股份副总王盛收警示函 减持套现百万元未预先披露",
    "href": "http://stock.jrj.com.cn/2020/07/01151030110973.shtml",
    "datetime": "2020-07-01 15:10:00",
    "code": "002203"
  },
  {
    "title": "[海亮股份]省委表彰!曹建国同志获 “浙江省优秀共产党员”称号",
    "href": "http://stock.jrj.com.cn/2020/06/24000030079652.shtml",
    "datetime": "2020-06-24 00:00:00",
    "code": "002203"
  },
  {
    "title": "[海亮股份]海亮集团获授“2020年抗击疫情卓越贡献奖”等两项殊荣",
    "href": "http://stock.jrj.com.cn/2020/06/23000029998086.shtml",
    "datetime": "2020-06-23 00:00:00",
    "code": "002203"
  },
  {
    "title": "[海亮股份]捐赠10.68亿元,海亮集团获年度中国十大慈善企业殊荣",
    "href": "http://stock.jrj.com.cn/2020/06/18000029956312.shtml",
    "datetime": "2020-06-18 00:00:00",
    "code": "002203"
  },
  {
    "title": "海亮股份控股股东海亮集团质押1200万股 用于可交换公司债券事项补充担保",
    "href": "http://stock.jrj.com.cn/2020/06/15182029929452.shtml",
    "datetime": "2020-06-15 18:20:57",
    "code": "002203"
  },
  {
    "title": "[海亮股份]海亮集团向诸暨市急救中心交付捐赠7台负压救护车·",
    "href": "http://stock.jrj.com.cn/2020/06/12000029923930.shtml",
    "datetime": "2020-06-12 00:00:00",
    "code": "002203"
  },
  {
    "title": "[海亮股份]海亮集团位列2017-2019年浙江本土民营跨国公司20强",
    "href": "http://stock.jrj.com.cn/2020/06/12000029923933.shtml",
    "datetime": "2020-06-12 00:00:00",
    "code": "002203"
  },
  {
    "title": "[海亮股份]海亮集团董事局主席顺利交棒",
    "href": "http://stock.jrj.com.cn/2020/06/11000029903638.shtml",
    "datetime": "2020-06-11 00:00:00",
    "code": "002203"
  },
  {
    "title": "[海亮股份]海亮股份(002203)调入深证F120指数",
    "href": "http://stock.jrj.com.cn/2020/06/10000029899889.shtml",
    "datetime": "2020-06-10 00:00:00",
    "code": "002203"
  },
  {
    "title": "[海亮股份]“微”力无穷 提高新媒体“吸粉”技巧 ——海亮集团举办笔杆子队伍第三期培训讲座",
    "href": "http://stock.jrj.com.cn/2020/06/09000029899892.shtml",
    "datetime": "2020-06-09 00:00:00",
    "code": "002203"
  },
  {
    "title": "[海亮股份]形象升级!明康汇生鲜菜市发力杭州老城区",
    "href": "http://stock.jrj.com.cn/2020/06/08000029899890.shtml",
    "datetime": "2020-06-08 00:00:00",
    "code": "002203"
  },
  {
    "title": "[海亮股份]集团董事长、党委书记曹建国受邀参加长三角企业家联盟成立大会,并出任联盟首批理事",
    "href": "http://stock.jrj.com.cn/2020/06/08000029899891.shtml",
    "datetime": "2020-06-08 00:00:00",
    "code": "002203"
  },
  {
    "title": "[海亮股份]银企合作 互利共赢 | 海亮集团与中国工商银行签署战略合作协议",
    "href": "http://stock.jrj.com.cn/2020/06/03000029845252.shtml",
    "datetime": "2020-06-03 00:00:00",
    "code": "002203"
  },
  {
    "title": "[海亮股份]曹建国出席首场“亲清直通车·政企恳谈会”并建言",
    "href": "http://stock.jrj.com.cn/2020/06/02000029845250.shtml",
    "datetime": "2020-06-02 00:00:00",
    "code": "002203"
  },
  {
    "title": "[海亮股份]为了自闭症群体,开地铁专列推催泪短剧,海亮这次拼了",
    "href": "http://stock.jrj.com.cn/2020/05/19000029712897.shtml",
    "datetime": "2020-05-19 00:00:00",
    "code": "002203"
  },
  {
    "title": "海亮股份国际化战略布局+智能制造 去年净利润超10亿元",
    "href": "http://stock.jrj.com.cn/2020/05/05210729579702.shtml",
    "datetime": "2020-05-05 21:07:05",
    "code": "002203"
  },
  {
    "title": "海亮股份2020年第一季度盈利1.68亿 同比减少43.88%",
    "href": "http://stock.jrj.com.cn/2020/05/03145129497534.shtml",
    "datetime": "2020-05-03 14:51:28",
    "code": "002203"
  },
  {
    "title": "海亮股份2019年实现净利润10.63亿元 将加速全球化布局及智能化制造",
    "href": "http://stock.jrj.com.cn/2020/05/03071229486806.shtml",
    "datetime": "2020-05-03 07:12:00",
    "code": "002203"
  },
  {
    "title": "海亮股份2019年净利10.63亿较上年同期增长17.06% 销量同比增长",
    "href": "http://stock.jrj.com.cn/2020/04/29205529423083.shtml",
    "datetime": "2020-04-29 20:55:56",
    "code": "002203"
  },
  {
    "title": "[海亮股份]海亮有色材料智造美国生产基地建设项目安全复工进行时",
    "href": "http://stock.jrj.com.cn/2020/04/28000029425290.shtml",
    "datetime": "2020-04-28 00:00:00",
    "code": "002203"
  },
  {
    "title": "[海亮股份]【海亮故事】开学季:海亮方案海亮人",
    "href": "http://stock.jrj.com.cn/2020/04/24000029389054.shtml",
    "datetime": "2020-04-24 00:00:00",
    "code": "002203"
  },
  {
    "title": "[海亮股份]海亮股份:智造一个“生态圈”",
    "href": "http://stock.jrj.com.cn/2020/04/21000029342809.shtml",
    "datetime": "2020-04-21 00:00:00",
    "code": "002203"
  },
  {
    "title": "[海亮股份]重磅|海亮明德院正式成立,致力打造具有一流领导力的核心管理团队",
    "href": "http://stock.jrj.com.cn/2020/04/20000029330243.shtml",
    "datetime": "2020-04-20 00:00:00",
    "code": "002203"
  },
  {
    "title": "[海亮股份]【海亮故事】1800多个小故事汇聚成的大爱之歌",
    "href": "http://stock.jrj.com.cn/2020/04/17000029330244.shtml",
    "datetime": "2020-04-17 00:00:00",
    "code": "002203"
  },
  {
    "title": "[海亮股份]【海亮故事】明康汇生鲜“十二时辰”",
    "href": "http://stock.jrj.com.cn/2020/04/03000029186387.shtml",
    "datetime": "2020-04-03 00:00:00",
    "code": "002203"
  },
  {
    "title": "[海亮股份]海亮教育科研大厦被列入滨江区领导联系的重点工程",
    "href": "http://stock.jrj.com.cn/2020/04/03000029186388.shtml",
    "datetime": "2020-04-03 00:00:00",
    "code": "002203"
  },
  {
    "title": "[海亮股份]白衣执甲,今朝凯旋!海亮仙居研学营地最高规格致敬战疫英雄",
    "href": "http://stock.jrj.com.cn/2020/03/31000029167721.shtml",
    "datetime": "2020-03-31 00:00:00",
    "code": "002203"
  },
  {
    "title": "[海亮股份]喜报 | “海亮转债”获第十三届新财富最佳可转债项目",
    "href": "http://stock.jrj.com.cn/2020/03/21000029082215.shtml",
    "datetime": "2020-03-21 00:00:00",
    "code": "002203"
  },
  {
    "title": "[海亮股份]喜讯|海亮股份董事长兼总经理朱张泉获“绍兴市高质量发展奖”先进个人",
    "href": "http://stock.jrj.com.cn/2020/03/18000029051483.shtml",
    "datetime": "2020-03-18 00:00:00",
    "code": "002203"
  },
  {
    "title": "[海亮股份]浙江省召开制造业高质量发展大会 海亮集团被授予“雄鹰行动”培育企业",
    "href": "http://stock.jrj.com.cn/2020/03/17000029043780.shtml",
    "datetime": "2020-03-17 00:00:00",
    "code": "002203"
  },
  {
    "title": "[海亮股份]海亮集团向诸暨市急救中心捐赠7辆救护车",
    "href": "http://stock.jrj.com.cn/2020/03/12000029009439.shtml",
    "datetime": "2020-03-12 00:00:00",
    "code": "002203"
  },
  {
    "title": "[海亮股份]中国银行浙江省分行吴敏行长一行莅临海亮集团调研指导",
    "href": "http://stock.jrj.com.cn/2020/03/11000029000972.shtml",
    "datetime": "2020-03-11 00:00:00",
    "code": "002203"
  },
  {
    "title": "[海亮股份]海亮集团荣获诸暨市“高质量发展突出贡献单位”“创业创新集体”荣誉",
    "href": "http://stock.jrj.com.cn/2020/03/09000028991175.shtml",
    "datetime": "2020-03-09 00:00:00",
    "code": "002203"
  },
  {
    "title": "[海亮股份]诸暨市委副书记、市长胡华良调研海亮集团并颁发世界500强荣誉奖",
    "href": "http://stock.jrj.com.cn/2020/03/07000028979636.shtml",
    "datetime": "2020-03-07 00:00:00",
    "code": "002203"
  },
  {
    "title": "[海亮股份]海亮有爱|一封封画信,架起爱的桥梁,一起为湖北的同学们加油",
    "href": "http://stock.jrj.com.cn/2020/03/04000028953173.shtml",
    "datetime": "2020-03-04 00:00:00",
    "code": "002203"
  },
  {
    "title": "[海亮股份]杭州市召开“战疫情 促发展”工作推进会 海亮集团获“点赞”",
    "href": "http://stock.jrj.com.cn/2020/03/03000028944857.shtml",
    "datetime": "2020-03-03 00:00:00",
    "code": "002203"
  },
  {
    "title": "[海亮股份]广东省汕尾市委书记张晓强调研海亮明康汇海丰种植基地",
    "href": "http://stock.jrj.com.cn/2020/02/29000028936676.shtml",
    "datetime": "2020-02-29 00:00:00",
    "code": "002203"
  },
  {
    "title": "[海亮股份]浙江省委常委、组织部长黄建发莅临海亮股份 调研指导疫情防控和复工复产工作",
    "href": "http://stock.jrj.com.cn/2020/02/28000028914220.shtml",
    "datetime": "2020-02-28 00:00:00",
    "code": "002203"
  },
  {
    "title": "[海亮股份]海亮教育科研大厦安全高效复工复建",
    "href": "http://stock.jrj.com.cn/2020/02/28000028916812.shtml",
    "datetime": "2020-02-28 00:00:00",
    "code": "002203"
  },
  {
    "title": "海亮股份2019年净利润10.6亿元增长17% 铜加工材销量增长",
    "href": "http://stock.jrj.com.cn/2020/02/27210528908889.shtml",
    "datetime": "2020-02-27 21:05:03",
    "code": "002203"
  },
  {
    "title": "[海亮股份]智能制造助力海亮股份:科学控疫情 统筹谋发展",
    "href": "http://stock.jrj.com.cn/2020/02/27000028906400.shtml",
    "datetime": "2020-02-27 00:00:00",
    "code": "002203"
  },
  {
    "title": "[海亮股份]海亮有爱|孩子居家抗疫,如何做好家庭教育叶翠微校长为您给出“锦囊妙计”",
    "href": "http://stock.jrj.com.cn/2020/02/27000028916810.shtml",
    "datetime": "2020-02-27 00:00:00",
    "code": "002203"
  },
  {
    "title": "[海亮股份]海亮有爱 | 疫情当前,宅家如何保护视力",
    "href": "http://stock.jrj.com.cn/2020/02/26000028897066.shtml",
    "datetime": "2020-02-26 00:00:00",
    "code": "002203"
  },
  {
    "title": "[海亮股份]湖州市委书记马晓晖调研海亮湖州国际康养度假小镇",
    "href": "http://stock.jrj.com.cn/2020/02/25000028889905.shtml",
    "datetime": "2020-02-25 00:00:00",
    "code": "002203"
  },
  {
    "title": "[海亮股份]媒体聚焦|海亮集团“码上复工” 上万员工每天打卡报平安",
    "href": "http://stock.jrj.com.cn/2020/02/24000028888453.shtml",
    "datetime": "2020-02-24 00:00:00",
    "code": "002203"
  },
  {
    "title": "[海亮股份]省商务厅厅长盛秋平调研指导海亮集团复工复产工作",
    "href": "http://stock.jrj.com.cn/2020/02/24000028889906.shtml",
    "datetime": "2020-02-24 00:00:00",
    "code": "002203"
  },
  {
    "title": "[海亮股份]杭州这家企业食堂走进去一看!全是“包厢”!",
    "href": "http://stock.jrj.com.cn/2020/02/23000028882118.shtml",
    "datetime": "2020-02-23 00:00:00",
    "code": "002203"
  },
  {
    "title": "[海亮股份]公益云课堂上线",
    "href": "http://stock.jrj.com.cn/2020/02/21000028882120.shtml",
    "datetime": "2020-02-21 00:00:00",
    "code": "002203"
  },
  {
    "title": "[海亮股份]想见你,海亮!",
    "href": "http://stock.jrj.com.cn/2020/02/20000028863703.shtml",
    "datetime": "2020-02-20 00:00:00",
    "code": "002203"
  },
  {
    "title": "[海亮股份]点赞!海亮教育公益云课堂登上“学习强国”学习平台!",
    "href": "http://stock.jrj.com.cn/2020/02/18000028849686.shtml",
    "datetime": "2020-02-18 00:00:00",
    "code": "002203"
  },
  {
    "title": "[海亮股份]“菜篮子”里的保卫战,我们在前线",
    "href": "http://stock.jrj.com.cn/2020/02/16000028849684.shtml",
    "datetime": "2020-02-16 00:00:00",
    "code": "002203"
  },
  {
    "title": "[海亮股份]加油站里能\"买\"菜这是真的!明康汇携手中国石化共建\"云厨房\"",
    "href": "http://stock.jrj.com.cn/2020/02/15000028849683.shtml",
    "datetime": "2020-02-15 00:00:00",
    "code": "002203"
  },
  {
    "title": "[海亮股份]爱的告白 | 我们在一起!海亮教育原创战疫MV《爱在徜徉》发布",
    "href": "http://stock.jrj.com.cn/2020/02/14000028882115.shtml",
    "datetime": "2020-02-14 00:00:00",
    "code": "002203"
  },
  {
    "title": "[海亮股份]厉兵秣马,复工战疫!海亮股份在行动!",
    "href": "http://stock.jrj.com.cn/2020/02/13000028849680.shtml",
    "datetime": "2020-02-13 00:00:00",
    "code": "002203"
  },
  {
    "title": "[海亮股份]海亮教育携手人民日报客户端、新华网客户端共推公益云课堂,让大爱惠及天下学子",
    "href": "http://stock.jrj.com.cn/2020/02/13000028849685.shtml",
    "datetime": "2020-02-13 00:00:00",
    "code": "002203"
  },
  {
    "title": "[海亮股份]复学前与复学后,幼儿园怎样保证宝贝的安全海亮学前教育集团用一份专业的《指引》给出答案",
    "href": "http://stock.jrj.com.cn/2020/02/12000028849682.shtml",
    "datetime": "2020-02-12 00:00:00",
    "code": "002203"
  },
  {
    "title": "[海亮股份]班级、课程不变,老师化身“网红主播”,海亮云端教室开课啦",
    "href": "http://stock.jrj.com.cn/2020/02/11000028849681.shtml",
    "datetime": "2020-02-11 00:00:00",
    "code": "002203"
  },
  {
    "title": "[海亮股份]柬埔寨男孩沙利:武汉加油!中国加油!",
    "href": "http://stock.jrj.com.cn/2020/02/10000028838826.shtml",
    "datetime": "2020-02-10 00:00:00",
    "code": "002203"
  },
  {
    "title": "[海亮股份]买菜不出门,鲜菜送到家!家庭套餐一次购齐!",
    "href": "http://stock.jrj.com.cn/2020/02/10000028838825.shtml",
    "datetime": "2020-02-10 00:00:00",
    "code": "002203"
  },
  {
    "title": "[海亮股份]海亮教育明天“开学”啦!赶紧来领取线上教材和参考资料哦!",
    "href": "http://stock.jrj.com.cn/2020/02/09000028838827.shtml",
    "datetime": "2020-02-09 00:00:00",
    "code": "002203"
  },
  {
    "title": "[海亮股份]海亮股份:致全体客户、经销商与合作伙伴的倡议书",
    "href": "http://stock.jrj.com.cn/2020/02/08000028838824.shtml",
    "datetime": "2020-02-08 00:00:00",
    "code": "002203"
  },
  {
    "title": "[海亮股份]战“疫”故事|“我是党员,我先上”,这个元宵,请向他们致敬!",
    "href": "http://stock.jrj.com.cn/2020/02/08000028838822.shtml",
    "datetime": "2020-02-08 00:00:00",
    "code": "002203"
  },
  {
    "title": "[海亮股份]基地前沿 | 以勇之名,全力以赴!",
    "href": "http://stock.jrj.com.cn/2020/02/07000028838823.shtml",
    "datetime": "2020-02-07 00:00:00",
    "code": "002203"
  },
  {
    "title": "[海亮股份]微光集大爱,疫情下的暖心瞬间",
    "href": "http://stock.jrj.com.cn/2020/02/06000028838819.shtml",
    "datetime": "2020-02-06 00:00:00",
    "code": "002203"
  },
  {
    "title": "海亮股份：第一批医疗用铜管出库 驰援全国各类防疫项目建设",
    "href": "http://stock.jrj.com.cn/2020/02/05164128776737.shtml",
    "datetime": "2020-02-05 16:41:16",
    "code": "002203"
  },
  {
    "title": "海亮股份第一批医疗防疫用铜管出库 驰援全国各类防疫项目建设",
    "href": "http://stock.jrj.com.cn/2020/02/05150228776427.shtml",
    "datetime": "2020-02-05 15:02:00",
    "code": "002203"
  },
  {
    "title": "[海亮股份]共克时艰 同心攻疫|海亮股份积极保障全国各类防疫项目的建设与运行",
    "href": "http://stock.jrj.com.cn/2020/02/05000028777304.shtml",
    "datetime": "2020-02-05 00:00:00",
    "code": "002203"
  },
  {
    "title": "[海亮股份]抗疫情!保民生!明康汇在行动!",
    "href": "http://stock.jrj.com.cn/2020/02/01000028775889.shtml",
    "datetime": "2020-02-01 00:00:00",
    "code": "002203"
  },
  {
    "title": "[海亮股份]停课不停学!面向全国中小学生的海亮名师公益云课堂喊你\"开学\"啦!",
    "href": "http://stock.jrj.com.cn/2020/01/26000028750089.shtml",
    "datetime": "2020-01-26 00:00:00",
    "code": "002203"
  },
  {
    "title": "[海亮股份]真情关怀暖人心︱海亮集团连续24年新春慰问困难群众",
    "href": "http://stock.jrj.com.cn/2020/01/19000028750088.shtml",
    "datetime": "2020-01-19 00:00:00",
    "code": "002203"
  },
  {
    "title": "[海亮股份]传承·奋斗·跨越|2020海亮大会圆满举行",
    "href": "http://stock.jrj.com.cn/2020/01/17000030406448.shtml",
    "datetime": "2020-01-17 00:00:00",
    "code": "002203"
  },
  {
    "title": "[海亮股份]湖州海亮国际康养度假小镇公开竞得四宗建设开发用地",
    "href": "http://stock.jrj.com.cn/2020/01/16000028689792.shtml",
    "datetime": "2020-01-16 00:00:00",
    "code": "002203"
  },
  {
    "title": "[海亮股份]海亮集团加入中国企业反舞弊联盟",
    "href": "http://stock.jrj.com.cn/2020/01/13000028672864.shtml",
    "datetime": "2020-01-13 00:00:00",
    "code": "002203"
  },
  {
    "title": "[海亮股份]有色智造 | 绍兴市委书记马卫光一行莅临海亮有色智造工业园调研指导",
    "href": "http://stock.jrj.com.cn/2020/01/03000028630903.shtml",
    "datetime": "2020-01-03 00:00:00",
    "code": "002203"
  },
  {
    "title": "[海亮股份]重磅!海亮教育学生接送高铁专列正式发车",
    "href": "http://stock.jrj.com.cn/2019/12/28000028603397.shtml",
    "datetime": "2019-12-28 00:00:00",
    "code": "002203"
  },
  {
    "title": "[海亮股份]顺应长三角一体化战略,海亮教育进驻安徽,芜湖海亮学校成功签约!",
    "href": "http://stock.jrj.com.cn/2019/12/28000028604738.shtml",
    "datetime": "2019-12-28 00:00:00",
    "code": "002203"
  },
  {
    "title": "[海亮股份]重磅讯息!刘信生教授出任兰州海亮教育园区总校长",
    "href": "http://stock.jrj.com.cn/2019/12/19000028557996.shtml",
    "datetime": "2019-12-19 00:00:00",
    "code": "002203"
  },
  {
    "title": "[海亮股份]以梦为马,奋力奔跑!海亮集团2019年环教育园健身跑开赛",
    "href": "http://stock.jrj.com.cn/2019/12/18000028553506.shtml",
    "datetime": "2019-12-18 00:00:00",
    "code": "002203"
  },
  {
    "title": "[海亮股份]海亮集团组织开展廉洁警示教育活动",
    "href": "http://stock.jrj.com.cn/2019/12/18000028557998.shtml",
    "datetime": "2019-12-18 00:00:00",
    "code": "002203"
  },
  {
    "title": "海亮股份控股股东减持966.62万张海亮转债",
    "href": "http://stock.jrj.com.cn/2019/12/17185528547149.shtml",
    "datetime": "2019-12-17 18:55:08",
    "code": "002203"
  },
  {
    "title": "海亮股份：控股股东减持966.62万张海亮转债",
    "href": "http://stock.jrj.com.cn/2019/12/17181328546945.shtml",
    "datetime": "2019-12-17 18:13:34",
    "code": "002203"
  },
  {
    "title": "海亮股份：控股股东海亮集团减持966.62万张海亮转债",
    "href": "http://stock.jrj.com.cn/2019/12/17180928546934.shtml",
    "datetime": "2019-12-17 18:09:00",
    "code": "002203"
  },
  {
    "title": "[海亮股份]海亮30年30人系列报道|平凡中不平凡的坚守",
    "href": "http://stock.jrj.com.cn/2019/12/17000028547319.shtml",
    "datetime": "2019-12-17 00:00:00",
    "code": "002203"
  },
  {
    "title": "[海亮股份]海亮30年30人系列报道|耐得住寂寞 守得住繁华",
    "href": "http://stock.jrj.com.cn/2019/12/13000028530947.shtml",
    "datetime": "2019-12-13 00:00:00",
    "code": "002203"
  },
  {
    "title": "[海亮股份]幸福样本:海亮集团组织700余名员工环游看世界",
    "href": "http://stock.jrj.com.cn/2019/12/12000030102500.shtml",
    "datetime": "2019-12-12 00:00:00",
    "code": "002203"
  },
  {
    "title": "[海亮股份]幸福样本:海亮集团组织700余名员工环游看世界",
    "href": "http://stock.jrj.com.cn/2019/12/12000028524342.shtml",
    "datetime": "2019-12-12 00:00:00",
    "code": "002203"
  },
  {
    "title": "[海亮股份]海亮30年30人系列报道|傲然盛放的铿锵玫瑰",
    "href": "http://stock.jrj.com.cn/2019/12/11000028524341.shtml",
    "datetime": "2019-12-11 00:00:00",
    "code": "002203"
  },
  {
    "title": "[海亮股份]海亮30年30人系列报道|“锱铢必较”的成本工作者",
    "href": "http://stock.jrj.com.cn/2019/12/10000028524340.shtml",
    "datetime": "2019-12-10 00:00:00",
    "code": "002203"
  },
  {
    "title": "[海亮股份]海亮教育布局浙东地区 ,“宁海公学”项目正式签约",
    "href": "http://stock.jrj.com.cn/2019/12/09000028509262.shtml",
    "datetime": "2019-12-09 00:00:00",
    "code": "002203"
  },
  {
    "title": "[海亮股份]喜讯 ▏2019浙江农业博览会明康汇再获金奖!",
    "href": "http://stock.jrj.com.cn/2019/12/05000028494774.shtml",
    "datetime": "2019-12-05 00:00:00",
    "code": "002203"
  },
  {
    "title": "[海亮股份]海亮30年30人系列报道|“小”作为 “大”贡献",
    "href": "http://stock.jrj.com.cn/2019/12/04000028489679.shtml",
    "datetime": "2019-12-04 00:00:00",
    "code": "002203"
  },
  {
    "title": "[海亮股份]海亮30年30人系列报道|做他乡热土上的园丁",
    "href": "http://stock.jrj.com.cn/2019/12/03000028484196.shtml",
    "datetime": "2019-12-03 00:00:00",
    "code": "002203"
  },
  {
    "title": "[海亮股份]海亮集团入选浙江省首批“雄鹰行动”培育企业",
    "href": "http://stock.jrj.com.cn/2019/12/02000028478723.shtml",
    "datetime": "2019-12-02 00:00:00",
    "code": "002203"
  },
  {
    "title": "[海亮股份]海亮30年30人系列报道|“没有任何借口”的去执行",
    "href": "http://stock.jrj.com.cn/2019/11/29000028469544.shtml",
    "datetime": "2019-11-29 00:00:00",
    "code": "002203"
  },
  {
    "title": "[海亮股份]海亮股份首次发行可转换公司债券 获市场热捧",
    "href": "http://stock.jrj.com.cn/2019/11/27000028459024.shtml",
    "datetime": "2019-11-27 00:00:00",
    "code": "002203"
  },
  {
    "title": "海亮股份首次成功发行可转换公司债券",
    "href": "http://stock.jrj.com.cn/2019/11/26221528454563.shtml",
    "datetime": "2019-11-26 22:15:00",
    "code": "002203"
  },
  {
    "title": "海亮股份31.5亿元可转债发行完成",
    "href": "http://stock.jrj.com.cn/2019/11/26211228454239.shtml",
    "datetime": "2019-11-26 21:12:48",
    "code": "002203"
  },
  {
    "title": "[海亮股份]有个关于杭州家长的大事件!",
    "href": "http://stock.jrj.com.cn/2019/11/22000028439174.shtml",
    "datetime": "2019-11-22 00:00:00",
    "code": "002203"
  },
  {
    "title": "[海亮股份]海亮30年30人系列报道|执着创新的海亮“魔术师”",
    "href": "http://stock.jrj.com.cn/2019/11/22000028451866.shtml",
    "datetime": "2019-11-22 00:00:00",
    "code": "002203"
  },
  {
    "title": "海亮股份控股股东海亮集团质押7300万股 2019年上半年净利同比增长17%",
    "href": "http://stock.jrj.com.cn/2019/11/21184028433561.shtml",
    "datetime": "2019-11-21 18:40:20",
    "code": "002203"
  },
  {
    "title": "[海亮股份]海亮30年30人系列报道|阎雪延:从普通外贸员到杰出员工,她靠得是这个",
    "href": "http://stock.jrj.com.cn/2019/11/20000028430807.shtml",
    "datetime": "2019-11-20 00:00:00",
    "code": "002203"
  },
  {
    "title": "[海亮股份]点赞!海亮获授两项浙江公益慈善最高奖",
    "href": "http://stock.jrj.com.cn/2019/11/19000028419883.shtml",
    "datetime": "2019-11-19 00:00:00",
    "code": "002203"
  },
  {
    "title": "[海亮股份]海亮开启5G+时代:海亮集团与中国移动签订战略合作协议",
    "href": "http://stock.jrj.com.cn/2019/11/19000028419884.shtml",
    "datetime": "2019-11-19 00:00:00",
    "code": "002203"
  },
  {
    "title": "[海亮股份]海亮30年30人系列报道|用心铸造幼教梦想",
    "href": "http://stock.jrj.com.cn/2019/11/18000028418473.shtml",
    "datetime": "2019-11-18 00:00:00",
    "code": "002203"
  },
  {
    "title": "[海亮股份]我们的热情High翻天——海亮集团2019年员工趣味运动会成功举办",
    "href": "http://stock.jrj.com.cn/2019/11/15000028412431.shtml",
    "datetime": "2019-11-15 00:00:00",
    "code": "002203"
  },
  {
    "title": "[海亮股份]海亮30年30人系列报道|一名教育工作者的“三为”初心",
    "href": "http://stock.jrj.com.cn/2019/11/15000028412432.shtml",
    "datetime": "2019-11-15 00:00:00",
    "code": "002203"
  },
  {
    "title": "[海亮股份]第五届世界浙商大会启幕 海亮集团获评“高质量发展”领军企业",
    "href": "http://stock.jrj.com.cn/2019/11/14000028397851.shtml",
    "datetime": "2019-11-14 00:00:00",
    "code": "002203"
  },
  {
    "title": "[海亮股份]海亮30年30人系列报道|匠心智造,铸国际精品",
    "href": "http://stock.jrj.com.cn/2019/11/13000028397850.shtml",
    "datetime": "2019-11-13 00:00:00",
    "code": "002203"
  },
  {
    "title": "[海亮股份]海亮30年30人系列报道|常年攻关在一线的总工",
    "href": "http://stock.jrj.com.cn/2019/11/12000028394613.shtml",
    "datetime": "2019-11-12 00:00:00",
    "code": "002203"
  },
  {
    "title": "[海亮股份]王敏涛同学获亚洲射击锦标赛冠军",
    "href": "http://stock.jrj.com.cn/2019/11/10000028377235.shtml",
    "datetime": "2019-11-10 00:00:00",
    "code": "002203"
  },
  {
    "title": "海亮股份股东海亮集团质押400万股 2019年上半年净利同比增长17%",
    "href": "http://stock.jrj.com.cn/2019/11/08094628369679.shtml",
    "datetime": "2019-11-08 09:46:48",
    "code": "002203"
  },
  {
    "title": "[海亮股份]清北“高才”如云而来,海亮教育又要“逆天”了",
    "href": "http://stock.jrj.com.cn/2019/11/08000028372736.shtml",
    "datetime": "2019-11-08 00:00:00",
    "code": "002203"
  },
  {
    "title": "[海亮股份]海亮30年30人系列报道|用时光丈量生命的宽度和深度",
    "href": "http://stock.jrj.com.cn/2019/11/08000028372737.shtml",
    "datetime": "2019-11-08 00:00:00",
    "code": "002203"
  },
  {
    "title": "[海亮股份]海亮30年30人系列报道|扎根教育坚守初心的典范",
    "href": "http://stock.jrj.com.cn/2019/11/07000028372735.shtml",
    "datetime": "2019-11-07 00:00:00",
    "code": "002203"
  },
  {
    "title": "[海亮股份]海亮30年30人系列报道|始终像新员工一样要求自己",
    "href": "http://stock.jrj.com.cn/2019/11/06000028366861.shtml",
    "datetime": "2019-11-06 00:00:00",
    "code": "002203"
  },
  {
    "title": "[海亮股份]海亮30年30人系列报道|平凡岗位,非凡的坚守",
    "href": "http://stock.jrj.com.cn/2019/11/05000028366860.shtml",
    "datetime": "2019-11-05 00:00:00",
    "code": "002203"
  },
  {
    "title": "[海亮股份]海亮30年30人系列报道|不改初心的行者",
    "href": "http://stock.jrj.com.cn/2019/11/04000028353889.shtml",
    "datetime": "2019-11-04 00:00:00",
    "code": "002203"
  },
  {
    "title": "[海亮股份]海亮30年30人系列报道|从操作工到总经理 勤勉走心是逆袭关键",
    "href": "http://stock.jrj.com.cn/2019/11/01000028340002.shtml",
    "datetime": "2019-11-01 00:00:00",
    "code": "002203"
  },
  {
    "title": "[海亮股份]喜报|海亮集团董事长曹建国获“有色金属标准化终身成就奖”荣誉称号",
    "href": "http://stock.jrj.com.cn/2019/11/01000028340001.shtml",
    "datetime": "2019-11-01 00:00:00",
    "code": "002203"
  },
  {
    "title": "海亮股份第三季度盈利1.76亿 同比增长25%",
    "href": "http://stock.jrj.com.cn/2019/10/31141128333021.shtml",
    "datetime": "2019-10-31 14:11:01",
    "code": "002203"
  },
  {
    "title": "[海亮股份]海亮30年30人系列报道|海亮“技术控”驱动有色智造未来",
    "href": "http://stock.jrj.com.cn/2019/10/31000028340000.shtml",
    "datetime": "2019-10-31 00:00:00",
    "code": "002203"
  },
  {
    "title": "[海亮股份]海亮30年30人系列报道|教学传奇的书写者",
    "href": "http://stock.jrj.com.cn/2019/10/30000028333127.shtml",
    "datetime": "2019-10-30 00:00:00",
    "code": "002203"
  },
  {
    "title": "海亮股份公开发行可转债申请获证监会核准批复",
    "href": "http://stock.jrj.com.cn/2019/10/29183428319269.shtml",
    "datetime": "2019-10-29 18:34:38",
    "code": "002203"
  },
  {
    "title": "[海亮股份]海亮30年30人系列报道|像家长般守护海亮教育",
    "href": "http://stock.jrj.com.cn/2019/10/29000028324206.shtml",
    "datetime": "2019-10-29 00:00:00",
    "code": "002203"
  },
  {
    "title": "[海亮股份]满满都是爱,海亮创业30年员工集体婚礼幕后花絮",
    "href": "http://stock.jrj.com.cn/2019/10/28000028319446.shtml",
    "datetime": "2019-10-28 00:00:00",
    "code": "002203"
  },
  {
    "title": "[海亮股份]海亮30年30人系列报道|在平凡岗位发光发热,一个越南“海亮人”的敬业情怀",
    "href": "http://stock.jrj.com.cn/2019/10/28000028319447.shtml",
    "datetime": "2019-10-28 00:00:00",
    "code": "002203"
  },
  {
    "title": "[海亮股份]30周年员工集体婚礼特辑|幸福是什么这是最美好的答案!",
    "href": "http://stock.jrj.com.cn/2019/10/24000028295310.shtml",
    "datetime": "2019-10-24 00:00:00",
    "code": "002203"
  },
  {
    "title": "[海亮股份]海亮30年30人系列报道|一个外籍教师的中国教育情怀",
    "href": "http://stock.jrj.com.cn/2019/10/22000028281125.shtml",
    "datetime": "2019-10-22 00:00:00",
    "code": "002203"
  },
  {
    "title": "[海亮股份]海亮30年30人系列报道|不要人夸颜色好 只留清气满乾坤",
    "href": "http://stock.jrj.com.cn/2019/10/21000028277919.shtml",
    "datetime": "2019-10-21 00:00:00",
    "code": "002203"
  },
  {
    "title": "[海亮股份]震撼!海亮版《我和我的祖国》MV来啦",
    "href": "http://stock.jrj.com.cn/2019/10/01000028254816.shtml",
    "datetime": "2019-10-01 00:00:00",
    "code": "002203"
  },
  {
    "title": "海亮股份股东Z&P公司减持5785万股 套现约5.87亿元",
    "href": "http://stock.jrj.com.cn/2019/09/26082028182642.shtml",
    "datetime": "2019-09-26 08:20:53",
    "code": "002203"
  },
  {
    "title": "[海亮股份]海亮集团召开第四次党员代表大会",
    "href": "http://stock.jrj.com.cn/2019/09/26000028184169.shtml",
    "datetime": "2019-09-26 00:00:00",
    "code": "002203"
  },
  {
    "title": "[海亮股份]海纳百川 初心永亮|海亮集团新党建厅开馆亮相",
    "href": "http://stock.jrj.com.cn/2019/09/26000028184170.shtml",
    "datetime": "2019-09-26 00:00:00",
    "code": "002203"
  },
  {
    "title": "[海亮股份]海亮教育科研大厦开工,造就教育发展新引擎",
    "href": "http://stock.jrj.com.cn/2019/09/26000028254817.shtml",
    "datetime": "2019-09-26 00:00:00",
    "code": "002203"
  },
  {
    "title": "[海亮股份]兰州引进海亮教育暨兰州海亮教育园区项目正式启动",
    "href": "http://stock.jrj.com.cn/2019/09/23000028167178.shtml",
    "datetime": "2019-09-23 00:00:00",
    "code": "002203"
  },
  {
    "title": "[海亮股份]大医精诚,海馨启航,杭州海亮馨蕙馨医院隆重举行开业庆典",
    "href": "http://stock.jrj.com.cn/2019/09/17000028167180.shtml",
    "datetime": "2019-09-17 00:00:00",
    "code": "002203"
  },
  {
    "title": "海亮股份半年报毛利率异常 新增产能未来能否消化存疑",
    "href": "http://stock.jrj.com.cn/2019/09/14094228130790.shtml",
    "datetime": "2019-09-14 09:42:32",
    "code": "002203"
  },
  {
    "title": "海亮股份副总经理违规减持股份 深交所下发监管函",
    "href": "http://stock.jrj.com.cn/2019/09/09152328109595.shtml",
    "datetime": "2019-09-09 15:23:55",
    "code": "002203"
  },
  {
    "title": "[海亮股份]海亮集团收购香港大学iClass互动学习平台版权",
    "href": "http://stock.jrj.com.cn/2019/09/05000028094713.shtml",
    "datetime": "2019-09-05 00:00:00",
    "code": "002203"
  },
  {
    "title": "[海亮股份]2019中国企业500强榜单发布,海亮集团连续16年入榜",
    "href": "http://stock.jrj.com.cn/2019/09/02000028080456.shtml",
    "datetime": "2019-09-02 00:00:00",
    "code": "002203"
  },
  {
    "title": "海亮股份2019年上半年净利6.44亿 收购KME项目",
    "href": "http://stock.jrj.com.cn/2019/08/28211428051220.shtml",
    "datetime": "2019-08-28 21:14:37",
    "code": "002203"
  },
  {
    "title": "海亮股份：2019年半年度报告主要财务指标",
    "href": "http://stock.jrj.com.cn/2019/08/28210028051123.shtml",
    "datetime": "2019-08-28 21:00:03",
    "code": "002203"
  },
  {
    "title": "[海亮股份]守正 善行 致远|海亮集团隆重举行30周年庆典活动",
    "href": "http://stock.jrj.com.cn/2019/08/23000028032790.shtml",
    "datetime": "2019-08-23 00:00:00",
    "code": "002203"
  },
  {
    "title": "[海亮股份]海亮爱心助成才,圆梦大学廿三载",
    "href": "http://stock.jrj.com.cn/2019/08/20000028032789.shtml",
    "datetime": "2019-08-20 00:00:00",
    "code": "002203"
  },
  {
    "title": "[海亮股份]浙勤集团党委书记董事长徐德良莅临海亮集团考察交流",
    "href": "http://stock.jrj.com.cn/2019/08/17000027993680.shtml",
    "datetime": "2019-08-17 00:00:00",
    "code": "002203"
  },
  {
    "title": "海亮股份：公开发行可转债申请获证监会通过",
    "href": "http://stock.jrj.com.cn/2019/08/11163727958693.shtml",
    "datetime": "2019-08-11 16:37:00",
    "code": "002203"
  },
  {
    "title": "[海亮股份]台州市长张晓强莅临海亮仙居研学园考察指导",
    "href": "http://stock.jrj.com.cn/2019/08/10000027959639.shtml",
    "datetime": "2019-08-10 00:00:00",
    "code": "002203"
  },
  {
    "title": "[海亮股份]浙江民营企业百强榜出炉,海亮集团荣登第三",
    "href": "http://stock.jrj.com.cn/2019/08/10000027959640.shtml",
    "datetime": "2019-08-10 00:00:00",
    "code": "002203"
  },
  {
    "title": "[海亮股份]国家机关事务管理局审计室主任范学臣一行调研海亮集团内部审计工作",
    "href": "http://stock.jrj.com.cn/2019/08/08000027959638.shtml",
    "datetime": "2019-08-08 00:00:00",
    "code": "002203"
  },
  {
    "title": "证监会：海亮股份发行可转债事项8月9日上会",
    "href": "http://stock.jrj.com.cn/2019/08/05183227931609.shtml",
    "datetime": "2019-08-05 18:32:00",
    "code": "002203"
  },
  {
    "title": "[海亮股份]严正声明",
    "href": "http://stock.jrj.com.cn/2019/07/19000027867835.shtml",
    "datetime": "2019-07-19 00:00:00",
    "code": "002203"
  },
  {
    "title": "[海亮股份]让员工放心,让孩子幸福|海亮一线员工子女暑期爱心托管班开班啦!",
    "href": "http://stock.jrj.com.cn/2019/07/16000027848082.shtml",
    "datetime": "2019-07-16 00:00:00",
    "code": "002203"
  },
  {
    "title": "[海亮股份]海星计划 | 青春不散场 少年又远方",
    "href": "http://stock.jrj.com.cn/2019/07/15000027842402.shtml",
    "datetime": "2019-07-15 00:00:00",
    "code": "002203"
  },
  {
    "title": "[海亮股份]中国有色金属加工工业协会致信感谢海亮集团",
    "href": "http://stock.jrj.com.cn/2019/07/12000027831433.shtml",
    "datetime": "2019-07-12 00:00:00",
    "code": "002203"
  },
  {
    "title": "[海亮股份]喜讯!《财富》中国500强揭晓:海亮股份位列222位,较2018年上升27位",
    "href": "http://stock.jrj.com.cn/2019/07/11000027827486.shtml",
    "datetime": "2019-07-11 00:00:00",
    "code": "002203"
  },
  {
    "title": "[海亮股份]感恩三十年 畅游看世界|海亮员工“全球之旅”起航",
    "href": "http://stock.jrj.com.cn/2019/07/10000027821139.shtml",
    "datetime": "2019-07-10 00:00:00",
    "code": "002203"
  },
  {
    "title": "[海亮股份]海亮教育落子兰州 明年9月迎首批学生",
    "href": "http://stock.jrj.com.cn/2019/07/08000027808953.shtml",
    "datetime": "2019-07-08 00:00:00",
    "code": "002203"
  },
  {
    "title": "[海亮股份]浙江省委常委、杭州市委书记周江勇一行莅临海亮(越南)铜业调研指导",
    "href": "http://stock.jrj.com.cn/2019/07/03000027808952.shtml",
    "datetime": "2019-07-03 00:00:00",
    "code": "002203"
  },
  {
    "title": "[海亮股份]1500万重奖中高考功勋团队,海亮教育“惊艳”了教育界",
    "href": "http://stock.jrj.com.cn/2019/07/01000028065877.shtml",
    "datetime": "2019-07-01 00:00:00",
    "code": "002203"
  },
  {
    "title": "[海亮股份]2019年中国铜加工产业年度大会暨中国(绍兴)铜产业发展高峰论坛召开",
    "href": "http://stock.jrj.com.cn/2019/07/01000028065883.shtml",
    "datetime": "2019-07-01 00:00:00",
    "code": "002203"
  },
  {
    "title": "[海亮股份]省市区人大、卫健委领导考察杭州海亮馨蕙馨医院",
    "href": "http://stock.jrj.com.cn/2019/06/27000027764713.shtml",
    "datetime": "2019-06-27 00:00:00",
    "code": "002203"
  },
  {
    "title": "海亮股份股东Z&P公司拟减持股份 预计减持不超总股本3%",
    "href": "http://stock.jrj.com.cn/2019/06/23101827743456.shtml",
    "datetime": "2019-06-23 10:18:41",
    "code": "002203"
  },
  {
    "title": "上市公司晚间利空公告：海亮股份股东拟减持不超3％",
    "href": "http://stock.jrj.com.cn/2019/06/21183227739649.shtml",
    "datetime": "2019-06-21 18:32:38",
    "code": "002203"
  },
  {
    "title": "海亮股份：持股14.79%的股东拟减持不超3%",
    "href": "http://stock.jrj.com.cn/2019/06/21180927739537.shtml",
    "datetime": "2019-06-21 18:09:55",
    "code": "002203"
  },
  {
    "title": "海亮股份股东拟减持公司股份不超过5856.32万股",
    "href": "http://stock.jrj.com.cn/2019/06/21180427739531.shtml",
    "datetime": "2019-06-21 18:04:25",
    "code": "002203"
  },
  {
    "title": "海亮股份：股东Z&P公司拟减持不超3%股份",
    "href": "http://stock.jrj.com.cn/2019/06/21174427739418.shtml",
    "datetime": "2019-06-21 17:44:00",
    "code": "002203"
  },
  {
    "title": "[海亮股份]海亮教育研究院满都拉博士荣获绍兴市“特聘专家”、“市级领军人才”称号",
    "href": "http://stock.jrj.com.cn/2019/06/19000027725674.shtml",
    "datetime": "2019-06-19 00:00:00",
    "code": "002203"
  },
  {
    "title": "[海亮股份]海亮教育研究院满都拉博士荣获绍兴市“特聘专家”、“市级领军人才”称号",
    "href": "http://stock.jrj.com.cn/2019/06/19000028065882.shtml",
    "datetime": "2019-06-19 00:00:00",
    "code": "002203"
  },
  {
    "title": "[海亮股份]海亮教育管理集团严正声明",
    "href": "http://stock.jrj.com.cn/2019/06/18000027720570.shtml",
    "datetime": "2019-06-18 00:00:00",
    "code": "002203"
  },
  {
    "title": "[海亮股份]海亮教育管理集团严正声明",
    "href": "http://stock.jrj.com.cn/2019/06/18000028065880.shtml",
    "datetime": "2019-06-18 00:00:00",
    "code": "002203"
  },
  {
    "title": "[海亮股份]海亮儿童发展研究院亮点产品首次发布",
    "href": "http://stock.jrj.com.cn/2019/06/18000027720569.shtml",
    "datetime": "2019-06-18 00:00:00",
    "code": "002203"
  },
  {
    "title": "[海亮股份]海亮中西部教育扶贫项目第一期启动",
    "href": "http://stock.jrj.com.cn/2019/06/14000027704264.shtml",
    "datetime": "2019-06-14 00:00:00",
    "code": "002203"
  },
  {
    "title": "[海亮股份]海亮中西部教育扶贫项目第一期启动",
    "href": "http://stock.jrj.com.cn/2019/06/14000028065881.shtml",
    "datetime": "2019-06-14 00:00:00",
    "code": "002203"
  },
  {
    "title": "[海亮股份]杭州海亮馨蕙馨医院顺利通过医疗执业验收许可审批",
    "href": "http://stock.jrj.com.cn/2019/06/14000027705515.shtml",
    "datetime": "2019-06-14 00:00:00",
    "code": "002203"
  },
  {
    "title": "[海亮股份]杭州海亮馨蕙馨医院顺利通过医疗执业验收许可审批",
    "href": "http://stock.jrj.com.cn/2019/06/14000028065879.shtml",
    "datetime": "2019-06-14 00:00:00",
    "code": "002203"
  },
  {
    "title": "[海亮股份]学习信息编写技巧 提高写作内功|海亮集团举办笔杆子队伍第二期培训讲座",
    "href": "http://stock.jrj.com.cn/2019/06/12000027693978.shtml",
    "datetime": "2019-06-12 00:00:00",
    "code": "002203"
  },
  {
    "title": "[海亮股份]学习信息编写技巧 提高写作内功|海亮集团举办笔杆子队伍第二期培训讲座",
    "href": "http://stock.jrj.com.cn/2019/06/12000027763576.shtml",
    "datetime": "2019-06-12 00:00:00",
    "code": "002203"
  },
  {
    "title": "[海亮股份]海亮集团助力中内协调研组召开浙江民企内部审计工作座谈会",
    "href": "http://stock.jrj.com.cn/2019/06/05000027669643.shtml",
    "datetime": "2019-06-05 00:00:00",
    "code": "002203"
  },
  {
    "title": "[海亮股份]海亮集团助力中内协调研组召开浙江民企内部审计工作座谈会",
    "href": "http://stock.jrj.com.cn/2019/06/05000027763575.shtml",
    "datetime": "2019-06-05 00:00:00",
    "code": "002203"
  },
  {
    "title": "[海亮股份]柬埔寨“网红”少年中国求学开启新生活",
    "href": "http://stock.jrj.com.cn/2019/06/03000027667852.shtml",
    "datetime": "2019-06-03 00:00:00",
    "code": "002203"
  },
  {
    "title": "[海亮股份]柬埔寨“网红”少年中国求学开启新生活",
    "href": "http://stock.jrj.com.cn/2019/06/03000027763574.shtml",
    "datetime": "2019-06-03 00:00:00",
    "code": "002203"
  },
  {
    "title": "[海亮股份]海亮教育对荣怀教育提起侵权诉讼",
    "href": "http://stock.jrj.com.cn/2019/05/27000027626184.shtml",
    "datetime": "2019-05-27 00:00:00",
    "code": "002203"
  },
  {
    "title": "[海亮股份]民建浙江省委会主委陈小平一行莅临海亮股份调研指导",
    "href": "http://stock.jrj.com.cn/2019/05/21000027763573.shtml",
    "datetime": "2019-05-21 00:00:00",
    "code": "002203"
  },
  {
    "title": "[海亮股份]民建浙江省委会主委陈小平一行莅临海亮股份调研指导",
    "href": "http://stock.jrj.com.cn/2019/05/21000027603952.shtml",
    "datetime": "2019-05-21 00:00:00",
    "code": "002203"
  },
  {
    "title": "[海亮股份]海亮集团携手国内外知名专家研讨“特需儿童康复”模式",
    "href": "http://stock.jrj.com.cn/2019/05/20000027606824.shtml",
    "datetime": "2019-05-20 00:00:00",
    "code": "002203"
  },
  {
    "title": "[海亮股份]海亮集团携手国内外知名专家研讨“特需儿童康复”模式",
    "href": "http://stock.jrj.com.cn/2019/05/20000027763572.shtml",
    "datetime": "2019-05-20 00:00:00",
    "code": "002203"
  },
  {
    "title": "[海亮股份]全国助残日前夕 | “江干区特殊儿童康复指导中心”落户海亮",
    "href": "http://stock.jrj.com.cn/2019/05/17000027591071.shtml",
    "datetime": "2019-05-17 00:00:00",
    "code": "002203"
  },
  {
    "title": "[海亮股份]华为集团常务董事汪涛莅临海亮集团考察交流",
    "href": "http://stock.jrj.com.cn/2019/05/10000027565030.shtml",
    "datetime": "2019-05-10 00:00:00",
    "code": "002203"
  },
  {
    "title": "海亮股份：已累计回购1.86%股份 耗资2.9亿元",
    "href": "http://stock.jrj.com.cn/2019/05/06182227530546.shtml",
    "datetime": "2019-05-06 18:22:09",
    "code": "002203"
  },
  {
    "title": "海亮股份一季度净利3亿元 同比增长20% 现金流量净额为3.15亿元",
    "href": "http://stock.jrj.com.cn/2019/05/05182227524673.shtml",
    "datetime": "2019-05-05 18:22:45",
    "code": "002203"
  },
  {
    "title": "[海亮股份]海亮集团入围2019中国慈善企业榜",
    "href": "http://stock.jrj.com.cn/2019/05/05000027525544.shtml",
    "datetime": "2019-05-05 00:00:00",
    "code": "002203"
  },
  {
    "title": "海亮股份去年净利9.09亿同比增29% 董事长朱张泉薪酬130万元",
    "href": "http://stock.jrj.com.cn/2019/05/04210427521681.shtml",
    "datetime": "2019-05-04 21:04:32",
    "code": "002203"
  },
  {
    "title": "全球产业基地布局持续优化 海亮股份去年营收超400亿",
    "href": "http://stock.jrj.com.cn/2019/04/30024327510197.shtml",
    "datetime": "2019-04-30 02:43:08",
    "code": "002203"
  },
  {
    "title": "[海亮股份]骄傲!浙江海亮股份有限公司董事长兼总经理朱张泉获评“浙江省劳动模范”",
    "href": "http://stock.jrj.com.cn/2019/04/30000027525541.shtml",
    "datetime": "2019-04-30 00:00:00",
    "code": "002203"
  },
  {
    "title": "海亮股份2018年净利同比增近三成 铜加工材销量69.53万吨",
    "href": "http://stock.jrj.com.cn/2019/04/28193927502655.shtml",
    "datetime": "2019-04-28 19:39:29",
    "code": "002203"
  },
  {
    "title": "[海亮股份]海亮·贫困听障儿童救助项目招募公告",
    "href": "http://stock.jrj.com.cn/2019/04/26000027503605.shtml",
    "datetime": "2019-04-26 00:00:00",
    "code": "002203"
  },
  {
    "title": "[海亮股份]2019年“海亮·雏鹰高飞”孤儿培养工程公告",
    "href": "http://stock.jrj.com.cn/2019/04/26000027503606.shtml",
    "datetime": "2019-04-26 00:00:00",
    "code": "002203"
  },
  {
    "title": "[海亮股份]全国招募!2019年“海亮·贫困少年英才培养工程”启动",
    "href": "http://stock.jrj.com.cn/2019/04/26000027503607.shtml",
    "datetime": "2019-04-26 00:00:00",
    "code": "002203"
  },
  {
    "title": "[海亮股份]重磅消息 | 10名清华北大优秀学子加盟海亮高级中学,助力海亮学子",
    "href": "http://stock.jrj.com.cn/2019/04/23000027465350.shtml",
    "datetime": "2019-04-23 00:00:00",
    "code": "002203"
  },
  {
    "title": "[海亮股份]首届“中国民办教育发展高峰论坛”在杭州举行",
    "href": "http://stock.jrj.com.cn/2019/04/20000027465352.shtml",
    "datetime": "2019-04-20 00:00:00",
    "code": "002203"
  },
  {
    "title": "[海亮股份]集团董事长兼总裁曹建国接任浙商总会公益慈善事业委员会2019年度轮值主席",
    "href": "http://stock.jrj.com.cn/2019/04/15000027395095.shtml",
    "datetime": "2019-04-15 00:00:00",
    "code": "002203"
  },
  {
    "title": "[海亮股份]重磅 | 海亮股份收购KME集团旗下铜合金棒和铜管业务完成交割",
    "href": "http://stock.jrj.com.cn/2019/04/02000027311266.shtml",
    "datetime": "2019-04-02 00:00:00",
    "code": "002203"
  },
  {
    "title": "[海亮股份]今年第三所国际研学营地!海亮教育牵手韩国仁川天空高中",
    "href": "http://stock.jrj.com.cn/2019/03/25000027227549.shtml",
    "datetime": "2019-03-25 00:00:00",
    "code": "002203"
  },
  {
    "title": "[海亮股份]安全生产永远是海亮的“天字号”工程",
    "href": "http://stock.jrj.com.cn/2019/03/18000027182545.shtml",
    "datetime": "2019-03-18 00:00:00",
    "code": "002203"
  },
  {
    "title": "[海亮股份]海亮教育又添四位绍兴市学科带头人!",
    "href": "http://stock.jrj.com.cn/2019/03/18000027182544.shtml",
    "datetime": "2019-03-18 00:00:00",
    "code": "002203"
  },
  {
    "title": "[海亮股份]国际铜加工协会(IWCC)来海亮(安徽)铜业交流学习",
    "href": "http://stock.jrj.com.cn/2019/03/12000027154621.shtml",
    "datetime": "2019-03-12 00:00:00",
    "code": "002203"
  },
  {
    "title": "[海亮股份]与布莱顿文法学校签署协议,海亮教育再添国际研学营地",
    "href": "http://stock.jrj.com.cn/2019/03/12000027154623.shtml",
    "datetime": "2019-03-12 00:00:00",
    "code": "002203"
  },
  {
    "title": "[海亮股份]海纳百川,缘来有你——记海亮馨蕙馨医院新员工训练营",
    "href": "http://stock.jrj.com.cn/2019/03/06000027125999.shtml",
    "datetime": "2019-03-06 00:00:00",
    "code": "002203"
  },
  {
    "title": "[海亮股份]海纳百川,缘来有你——记海亮馨蕙馨医院新员工训练营",
    "href": "http://stock.jrj.com.cn/2019/03/06000028065875.shtml",
    "datetime": "2019-03-06 00:00:00",
    "code": "002203"
  },
  {
    "title": "[海亮股份]再添国际研学营地!海亮教育与托马斯卡中学签署友好学校协议",
    "href": "http://stock.jrj.com.cn/2019/03/01000027106151.shtml",
    "datetime": "2019-03-01 00:00:00",
    "code": "002203"
  },
  {
    "title": "海亮股份：已累计回购1.03%股份 耗资1.56亿元",
    "href": "http://stock.jrj.com.cn/hotstock/2019/02/15075927046292.shtml",
    "datetime": "2019-02-15 07:59:55",
    "code": "002203"
  },
  {
    "title": "[海亮股份]湖州市副市长闵云走访调研海亮康养度假小镇项目",
    "href": "http://stock.jrj.com.cn/2019/02/15000027063197.shtml",
    "datetime": "2019-02-15 00:00:00",
    "code": "002203"
  },
  {
    "title": "[海亮股份]海亮生态农业仙居研学基地入选首批浙江省中小学生研学实践教育基地",
    "href": "http://stock.jrj.com.cn/2019/02/15000027063196.shtml",
    "datetime": "2019-02-15 00:00:00",
    "code": "002203"
  },
  {
    "title": "海亮股份：回购公司股份比例达1% 耗资1.56亿元",
    "href": "http://stock.jrj.com.cn/2019/02/14171827044365.shtml",
    "datetime": "2019-02-14 17:18:00",
    "code": "002203"
  },
  {
    "title": "[海亮股份]海亮集团完成新一轮债券回购工作",
    "href": "http://stock.jrj.com.cn/2019/02/14000027044657.shtml",
    "datetime": "2019-02-14 00:00:00",
    "code": "002203"
  },
  {
    "title": "[海亮股份]真情关怀暖人心|海亮集团连续23年新春慰问困难群众",
    "href": "http://stock.jrj.com.cn/2019/02/01000027012869.shtml",
    "datetime": "2019-02-01 00:00:00",
    "code": "002203"
  },
  {
    "title": "[海亮股份]三十载惊涛拍岸,九万里风鹏正举|海亮集团2019新春团拜会精彩集锦",
    "href": "http://stock.jrj.com.cn/2019/01/31000028065878.shtml",
    "datetime": "2019-01-31 00:00:00",
    "code": "002203"
  },
  {
    "title": "[海亮股份]三十载惊涛拍岸,九万里风鹏正举|海亮集团2019新春团拜会精彩集锦",
    "href": "http://stock.jrj.com.cn/2019/01/31000027012868.shtml",
    "datetime": "2019-01-31 00:00:00",
    "code": "002203"
  },
  {
    "title": "海亮股份收购铜棒行业龙头抢滩欧洲市场",
    "href": "http://stock.jrj.com.cn/2019/01/30031426999330.shtml",
    "datetime": "2019-01-30 03:14:04",
    "code": "002203"
  },
  {
    "title": "海亮股份1.19亿欧元海外并购抢占欧洲高档铜合金棒市场",
    "href": "http://stock.jrj.com.cn/2019/01/29063126994925.shtml",
    "datetime": "2019-01-29 06:31:00",
    "code": "002203"
  },
  {
    "title": "海亮股份1.19亿欧元海外并购 抢占欧洲高档铜合金棒市场",
    "href": "http://stock.jrj.com.cn/2019/01/28210426993404.shtml",
    "datetime": "2019-01-28 21:04:00",
    "code": "002203"
  },
  {
    "title": "海亮股份：收购KME旗下铜合金棒和铜管业务相关资产",
    "href": "http://stock.jrj.com.cn/2019/01/28190026993045.shtml",
    "datetime": "2019-01-28 19:00:00",
    "code": "002203"
  },
  {
    "title": "[海亮股份]牛津大学为何频频造访海亮 这所学校到底有何魔力",
    "href": "http://stock.jrj.com.cn/2019/01/18000028065876.shtml",
    "datetime": "2019-01-18 00:00:00",
    "code": "002203"
  },
  {
    "title": "[海亮股份]海亮集团举办第一期“笔杆子”队伍启动会暨公文写作讲座",
    "href": "http://stock.jrj.com.cn/2019/01/16000026912378.shtml",
    "datetime": "2019-01-16 00:00:00",
    "code": "002203"
  }
]